astropitography/AstroPitography.py
astropitography/__init__.py
astropitography/__main__.py
astropitography/blackimage.png
astropitography/camera_manager.py
astropitography/crosshair.png
astropitography/gui_manager.py
astropitography/settings.py
astropitography/tetra3.py
astropitography/utils.py
astropitography/version.py
astropitography/db/default_database.npz
astropitography-0.0.3.dist-info/LICENSE
astropitography-0.0.3.dist-info/METADATA
astropitography-0.0.3.dist-info/WHEEL
astropitography-0.0.3.dist-info/entry_points.txt
astropitography-0.0.3.dist-info/top_level.txt
astropitography-0.0.3.dist-info/RECORD
