Metadata-Version: 2.1
Name: astropitography
Version: 0.0.3
Summary: Astrophotography + raspberry pi HQ camera = AstroPitography
Author-email: Adam Baskerville <adamlukebaskerville@gmail.com>
Maintainer-email: Adam Baskerville <adamlukebaskerville@gmail.com>, Daniel Opara <daniel.opara@tufts.edu>
License: MIT License
Project-URL: Homepage, https://adambaskerville.github.io/tabs/astro/
Keywords: astrophotography,raspberry pi
Classifier: Development Status :: 5 - Production/Stable
Classifier: Intended Audience :: Developers
Classifier: Intended Audience :: Science/Research
Classifier: Intended Audience :: Education
Classifier: Topic :: Education
Classifier: Topic :: Multimedia :: Graphics :: Capture :: Digital Camera
Classifier: Topic :: Multimedia :: Video :: Capture
Classifier: Topic :: Scientific/Engineering :: Astronomy
Classifier: Topic :: Scientific/Engineering :: Image Processing
Classifier: Topic :: Software Development :: Build Tools
Classifier: License :: OSI Approved :: MIT License
Classifier: Programming Language :: Python :: 3
Classifier: Programming Language :: Python :: 3 :: Only
Requires-Python: >=3.8
License-File: LICENSE
Requires-Dist: scipy ==1.8.1
Requires-Dist: numpy ==1.24.3
Requires-Dist: picamera >=1.12
Requires-Dist: pidng >=3.4.7
Requires-Dist: Pillow >=8.4.0
Requires-Dist: PySimpleGUI <=4.60.5
Provides-Extra: dev
Requires-Dist: nox ; extra == 'dev'
Requires-Dist: pre-commit ; extra == 'dev'
Provides-Extra: docs
Requires-Dist: sphinx !=5.1.0 ; extra == 'docs'
Requires-Dist: sphinx-sitemap ; extra == 'docs'
Requires-Dist: sphinx-inline-tabs ; extra == 'docs'
Requires-Dist: sphinx-book-theme ; extra == 'docs'
Requires-Dist: sphinx-design ; extra == 'docs'
Requires-Dist: sphinx-toolbox ; extra == 'docs'
Requires-Dist: sphinx-togglebutton ; extra == 'docs'
Requires-Dist: jupytext >=1.11.2 ; extra == 'docs'
Requires-Dist: myst-nb ; extra == 'docs'
Requires-Dist: screeninfo ; extra == 'docs'
Provides-Extra: test
Requires-Dist: pytest >=6 ; extra == 'test'
Requires-Dist: pytest-cov >=3 ; extra == 'test'
